CHANGES.rst
COPYING
MANIFEST.in
README.rst
setup.py
django_vff.egg-info/PKG-INFO
django_vff.egg-info/SOURCES.txt
django_vff.egg-info/dependency_links.txt
django_vff.egg-info/not-zip-safe
django_vff.egg-info/requires.txt
django_vff.egg-info/top_level.txt
vff/__init__.py
vff/abcs.py
vff/field.py
vff/git_backend.py
vff/storage.py