Metadata-Version: 1.0
Name: django-vff
Version: 0.1b3
Summary: Versioned file field for django models
Home-page: https://github.com/Yaco-Sistemas/django-vff
Author: TERENA
Author-email: eperez@yaco.es
License: BSD
Keywords: django versioned file field vcs model git
Platform: UNKNOWN
Classifier: Development Status :: 4 - Beta
Classifier: Framework :: Django
Classifier: Intended Audience :: Developers
Classifier: License :: OSI Approved :: BSD License
Classifier: Operating System :: OS Independent
Classifier: Programming Language :: Python
